{
    "last_update": "2026-07-19 07:18",
    "predictions": {
        "道奇 對 洋基": {
            "勝率": "66.55%",
            "最可能比分": "0:0",
            "錯誤率": "33.45%",
            "戰術分析": "全聯盟 30 隊模擬完畢"
        },
        "勇士 對 費城人": {
            "勝率": "67.23%",
            "最可能比分": "0:0",
            "錯誤率": "32.77%",
            "戰術分析": "全聯盟 30 隊模擬完畢"
        },
        "太空人 對 金鶯": {
            "勝率": "67.96%",
            "最可能比分": "0:0",
            "錯誤率": "32.04%",
            "戰術分析": "全聯盟 30 隊模擬完畢"
        },
        "教士 對 響尾蛇": {
            "勝率": "69.88%",
            "最可能比分": "0:0",
            "錯誤率": "30.12%",
            "戰術分析": "全聯盟 30 隊模擬完畢"
        }
    }
}